contuino/__init__.py
contuino/client_core.py
contuino/contuino_micropython/__init__.py
contuino/contuino_micropython/esp8266-20180511-v1.9.4.bin
contuino/contuino_micropython/mp_helpers.py
contuino/contuino_micropython/generated/__init__.py
contuino/contuino_micropython/generated/main.py
contuino/contuino_micropython/templates/__init__.py
contuino/contuino_micropython/templates/main_template.py
contuino-0.0.5.dev0.data/data/micropython_bin/esp8266-20180511-v1.9.4.bin
contuino-0.0.5.dev0.data/data/micropython_main_template/main_template.py
contuino-0.0.5.dev0.dist-info/LICENSE
contuino-0.0.5.dev0.dist-info/METADATA
contuino-0.0.5.dev0.dist-info/WHEEL
contuino-0.0.5.dev0.dist-info/top_level.txt
contuino-0.0.5.dev0.dist-info/RECORD
